runAM/__init__.py
runAM/__main__.py
runAM/cli.py
runAM/cli_spec.py
runAM/profile.py
runAM/server.py
runAM/db/JSONStore.py
runAM/db/__init__.py
runAM/generate/__init__.py
runAM/generate/port_config_data.py
runAM/read/__init__.py
runAM/read/yaml_file.py
runAM/read/yaml_string.py
runAM/tools/__init__.py
runAM/tools/change_nested_value.py
runAM/tools/merge_data_objects.py
runAM/tools/time_stamp.py
runAM_evpn-0.1.5.dist-info/LICENSE.txt
runAM_evpn-0.1.5.dist-info/METADATA
runAM_evpn-0.1.5.dist-info/WHEEL
runAM_evpn-0.1.5.dist-info/entry_points.txt
runAM_evpn-0.1.5.dist-info/top_level.txt
runAM_evpn-0.1.5.dist-info/RECORD
