Metadata-Version: 2.1
Name: runAM-evpn
Version: 0.1.5
Summary: runAM Python modules to build EVPN network
Home-page: https://github.com/arista-netdevops-community/runAM
Author: Petr Ankudinov
License: BSD
Platform: UNKNOWN
Classifier: License :: OSI Approved :: BSD License
Classifier: Programming Language :: Python :: 3
Classifier: Programming Language :: Python :: 3.8
Classifier: Development Status :: 3 - Alpha
Classifier: Operating System :: POSIX :: Linux
Requires-Dist: argcomplete (==1.12.1)
Requires-Dist: glom (==20.11.0)
Requires-Dist: jq (==1.1.1)
Requires-Dist: PyYAML (==5.3.1)
